shoopdaloop/__init__.py
shoopdaloop/__main__.py
shoopdaloop/description.txt
shoopdaloop/libshoop_accelerate.dylib
shoopdaloop/libshoop_crashhandling.dylib
shoopdaloop/libshoopdaloop.dylib
shoopdaloop/libshoopdaloop_bindings.py
shoopdaloop/qml_tests.py
shoopdaloop/shoop_accelerate.py
shoopdaloop/shoop_crashhandling.py
shoopdaloop/test_runner
shoopdaloop/version.txt
shoopdaloop/lib/Colorcodes.py
shoopdaloop/lib/__init__.py
shoopdaloop/lib/backend_wrappers.py
shoopdaloop/lib/cpp_imports.py
shoopdaloop/lib/crash_handling.py
shoopdaloop/lib/delay.js
shoopdaloop/lib/directories.py
shoopdaloop/lib/findChildItems.py
shoopdaloop/lib/findFirstParent.py
shoopdaloop/lib/flatten.py
shoopdaloop/lib/gen_click_track.py
shoopdaloop/lib/generate_session.js
shoopdaloop/lib/init_dynlibs.py
shoopdaloop/lib/js_constants.py
shoopdaloop/lib/logging.py
shoopdaloop/lib/lua_qobject_interface.py
shoopdaloop/lib/lua_qobject_interface_test.py
shoopdaloop/lib/midi.js
shoopdaloop/lib/midi_control.js
shoopdaloop/lib/midi_helpers.py
shoopdaloop/lib/mode_helpers.js
shoopdaloop/lib/mode_helpers.py
shoopdaloop/lib/qml_helpers.py
shoopdaloop/lib/qml_url_to_filename.js
shoopdaloop/lib/qt_thread_protected.py
shoopdaloop/lib/recursive_jsvalue_convert.py
shoopdaloop/lib/smf.py
shoopdaloop/lib/stereo.js
shoopdaloop/lib/type_checks.js
shoopdaloop/lib/types.py
shoopdaloop/resources/click_high.wav
shoopdaloop/resources/click_low.wav
shoopdaloop/resources/icon.xcf
shoopdaloop/resources/logo-small.png
shoopdaloop/resources/logo.png
shoopdaloop/resources/logo.xcf
shoopdaloop/resources/shaker_primary.wav
shoopdaloop/resources/shaker_secondary.wav
shoopdaloop/resources/shoopdawhoop.png
shoopdaloop/scripts/repeat_run_app.py
shoopdaloop/scripts/run_and_generate_coverage.sh
shoopdaloop/third_party/__init__.py
shoopdaloop/lib/q_objects/Application.py
shoopdaloop/lib/q_objects/ApplicationMetadata.py
shoopdaloop/lib/q_objects/AudioPort.py
shoopdaloop/lib/q_objects/AutoConnect.py
shoopdaloop/lib/q_objects/Backend.py
shoopdaloop-0.1.0.dist-info/LICENSE
shoopdaloop-0.1.0.dist-info/METADATA
shoopdaloop-0.1.0.dist-info/WHEEL
shoopdaloop-0.1.0.dist-info/entry_points.txt
shoopdaloop-0.1.0.dist-info/RECORD
