Metadata-Version: 2.1
Name: shoopdaloop
Version: 0.1.0
Summary: Live looping application with DAW elements.
Keywords: music midi jack looping
Author-Email: Sander Vocke <sandervocke@gmail.com>
Maintainer-Email: Sander Vocke <sandervocke@gmail.com>
License:                     GNU GENERAL PUBLIC LICENSE
Classifier: Development Status :: 2 - Pre-Alpha
Classifier: License :: OSI Approved :: GNU Lesser General Public License v2 or later (LGPLv2+)
Classifier: Programming Language :: Python :: 3 :: Only
Classifier: Programming Language :: Python :: 3.9
Classifier: Programming Language :: Python :: 3.9
Classifier: Programming Language :: Python :: 3.10
Classifier: Programming Language :: Python :: 3.11
Classifier: Programming Language :: Python :: 3.12
Classifier: Topic :: Multimedia :: Sound/Audio :: Capture/Recording
Classifier: Operating System :: POSIX :: Linux
Project-URL: Homepage, https://github.com/SanderVocke/shoopdaloop
Project-URL: Bug tracker, https://github.com/SanderVocke/shoopdaloop/issues
Project-URL: Discussions, https://github.com/SanderVocke/shoopdaloop/discussions
Requires-Python: >=3.9
Requires-Dist: soundfile==0.12.1
Requires-Dist: mido==1.3.2
Requires-Dist: jsonschema==4.22.0
Requires-Dist: numpy==1.26.4
Requires-Dist: pyjacklib==0.1.1
Requires-Dist: pyside6-essentials==6.6.3.1
Requires-Dist: lupa==2.2
Requires-Dist: appdirs==1.4.4
Requires-Dist: sounddevice==0.4.7
Requires-Dist: pywin32; platform_system == "Windows"
Requires-Dist: pytest; extra == "test"
Requires-Dist: sphinx; extra == "docs"
Requires-Dist: sphinx-material; extra == "docs"
Requires-Dist: sphinxcontrib-fulltoc; extra == "docs"
Requires-Dist: sphinxcontrib-plantuml; extra == "docs"
Provides-Extra: test
Provides-Extra: docs
